deeplite/deeplite_logging.cpython-37m-x86_64-linux-gnu.so
deeplite/package_signature.cpython-37m-x86_64-linux-gnu.so
deeplite/deeplite_encryption.cpython-37m-x86_64-linux-gnu.so
deeplite_tools-0.0.4.dist-info/METADATA
deeplite_tools-0.0.4.dist-info/RECORD
deeplite_tools-0.0.4.dist-info/top_level.txt
deeplite_tools-0.0.4.dist-info/LICENSE
deeplite_tools-0.0.4.dist-info/WHEEL
